[
    {
        "id": "10270",
        "name": "Los Angeles Angels at Seattle Mariners (English)",
        "url": "https://edgestreams.pro/hls/jzabfazkbf27.m3u8?st=zepSY9INY25T5wGSTzUduLaYhUIbC2Wf78PCkQAhrxM&e=1782880923"
    },
    {
        "id": "10271",
        "name": "Los Angeles Dodgers at Athletics Athletics (English)",
        "url": "https://edge2caster.pro/hls/hefbafbakx28.m3u8?st=sGXtNnwzvMFyQxzJzjEgT3FqkrA2B0qIN8AL3jI1OIk&e=1782880923"
    },
    {
        "id": "10272",
        "name": "San Francisco Giants at Arizona Diamondbacks (English)",
        "url": "https://mainstreams.pro/hls/hfzljfahzcax29.m3u8?st=RzQD582sZl_mLN1Pln8N9RPLpmwY2LfIQFC__k-Kfvk&e=1782880923"
    },
    {
        "id": "10257",
        "name": "Ecuador at Mexico (English)",
        "url": "https://edge2caster.pro/hls/24SDAZFcsqnj24.m3u8?st=Vect3I3e2frVm2Vxi58nETiIvWE5vf5npaWukAEJgbg&e=1782880924"
    },
    {
        "id": "10257",
        "name": "Ecuador at Mexico (Arabic)",
        "url": "https://mainstreams.pro/hls/eJmauBDCIf.m3u8?st=7BQqFe5IbKRlqhEveMSQgvGIsRSfAS_j4TYnbZVfvS0&e=1782880924"
    },
    {
        "id": "10257",
        "name": "Ecuador at Mexico (Spanish)",
        "url": "https://edge2caster.pro/hls/b0h5fNwDKH.m3u8?st=Ya35uebfdcoOtBopX5tnwlv5Z801NqN-OsBuxaddC6U&e=1782880924"
    },
    {
        "id": "10269",
        "name": "Miami Marlins at Colorado Rockies (English)",
        "url": "https://mainstreams.pro/hls/dzjhkfazbka26.m3u8?st=gWJNJpCRgY4I7AaASTBoB348CzRCoBX34pkRqwlHTng&e=1782880924"
    },
    {
        "id": "10268",
        "name": "Minnesota Twins at Houston Astros (English)",
        "url": "https://mainstreams.pro/hls/kjhfzua25.m3u8?st=P-rA_qiqUq5f_OuOJOFsTPIUPwIty6SfOGdN5sqzXrQ&e=1782880924"
    },
    {
        "id": "10267",
        "name": "San Diego Padres at Chicago Cubs (English)",
        "url": "https://mainstreams.pro/hls/fskjanach24.m3u8?st=paTCyNu3zkzDJrbCvnPBwO0nzEtl387jHplT-Rm3g1c&e=1782880924"
    },
    {
        "id": "10265",
        "name": "Cincinnati Reds at Milwaukee Brewers (English)",
        "url": "https://edgestreams.pro/hls/ijfnakfidch22.m3u8?st=WYMyvwzaAPLoemaDlywGBhgQc9Cr_URpTgLtb7vxnBA&e=1782880924"
    },
    {
        "id": "10266",
        "name": "Tampa Bay Rays at Kansas City Royals (English)",
        "url": "https://edge2caster.pro/hls/jnzkdzjfanch23.m3u8?st=KBL9_qJDOrL5vmmZmF8w8DcgKeV-grrNYLxL-kFyYyM&e=1782880924"
    },
    {
        "id": "10264",
        "name": "St. Louis Cardinals at Atlanta Braves (English)",
        "url": "https://edgestreams.pro/hls/ojzkajnach21.m3u8?st=NtZTyRB3AcoCvarhpHs30EwgbtgFX4Q9EkPkW-_sXug&e=1782880924"
    },
    {
        "id": "10263",
        "name": "Washington Nationals at Boston Red Sox (English)",
        "url": "https://edge2caster.pro/hls/jkzahzadach20.m3u8?st=IWrtGj8p4vwLfZreduH88JqOVE17bfaLMcqR7dF-XcE&e=1782880925"
    },
    {
        "id": "10262",
        "name": "New York Mets at Toronto Blue Jays (English)",
        "url": "https://edgestreams.pro/hls/bzagLHzach19.m3u8?st=M1_lrp1hbY0bEjpEtC-_uMdGOAGw5rm27pwpEiQcl00&e=1782880925"
    },
    {
        "id": "10261",
        "name": "Detroit Tigers at New York Yankees (English)",
        "url": "https://mainstreams.pro/hls/Czajafjihafch18.m3u8?st=rnimQ7tEznuVeUhQxK93YRciOB8gLhsfC15Wuk7r0qU&e=1782880925"
    },
    {
        "id": "10273",
        "name": "Las Vegas Aces at New York Liberty (English)",
        "url": "https://mainstreams.pro/hls/bvnsqdfvgha70.m3u8?st=QOhaDGP3Hh__RCN2f5jilD7HjNic5Xd2CP0gLXOBHn8&e=1782880925"
    },
    {
        "id": "10259",
        "name": "Pittsburgh Pirates at Philadelphia Phillies (English)",
        "url": "https://edge2caster.pro/hls/16yuitzaerghbhc16.m3u8?st=AL5HalMyFQXzuQjnTtjBQv6Z_KV3816BTYyqTP8CERQ&e=1782880925"
    },
    {
        "id": "10260",
        "name": "Texas Rangers at Cleveland Guardians (English)",
        "url": "https://edgestreams.pro/hls/ihfazugfyjcazich17.m3u8?st=Zi97CMvn-mUu9_zb2Qv0IYc_kZ7F_RJuLY1VqOg0c0s&e=1782880925"
    },
    {
        "id": "10258",
        "name": "Chicago White Sox at Baltimore Orioles (English)",
        "url": "https://mainstreams.pro/hls/dazhfiach15.m3u8?st=oowjlG5CWvnU3CXgdYyfIMmHMoUJpQ0R0S3F1qzekpU&e=1782880926"
    }
]