[
    {
        "id": "7419",
        "name": "Milwaukee Bucks at Phoenix Suns (English)",
        "url": "https://mainstreams.pro/hls/yjtzafghvjza74.m3u8?st=yOWzEaZtrKvABTe9Mf6lURPXvMJKzT3XjSboS1yGHzM&e=1773999780"
    },
    {
        "id": "7446",
        "name": "Tampa Bay Lightning at Edmonton Oilers (English)",
        "url": "https://mainstreams.pro/hls/cwxvbnfghq60.m3u8?st=VVJeXnLxxbjoBKsNNXbnHA26Olewo-hqsA_of1ifAuo&e=1773999780"
    },
    {
        "id": "7418",
        "name": "Philadelphia 76ers at Utah Jazz (English)",
        "url": "https://mainstreams.pro/hls/fdgsqdfawa73.m3u8?st=goyPJSOLQMYY9gDl_EJcbED5ZcJLX2xTgDePun32BKs&e=1773999780"
    },
    {
        "id": "7493",
        "name": "Chicago Cubs at Seattle Mariners (English)",
        "url": "https://mainstreams.pro/hls/hfzljfahzcax29.m3u8?st=az29KkJPaGGwbxZrNYflbADfiUGterOTiBoiIzY_vGs&e=1773999781"
    },
    {
        "id": "7492",
        "name": "Chicago White Sox at Cincinnati Reds (English)",
        "url": "https://mainstreams.pro/hls/hefbafbakx28.m3u8?st=ePPnqOW3zCrztMxsogEleCjRwxWOVc_VM1iDDEqOwKA&e=1773999781"
    },
    {
        "id": "7417",
        "name": "LA Clippers at Dallas Mavericks (English)",
        "url": "https://mainstreams.pro/hls/pllmazjkdzajh72.m3u8?st=PPiRM5BzOwjy7qWsZ1r80bRDfjIP_Ba3OAopXT1ds-o&e=1773999781"
    },
    {
        "id": "7414",
        "name": "Golden State Warriors at Atlanta Hawks (English)",
        "url": "https://mainstreams.pro/hls/zeafwqvhfe69.m3u8?st=R0nrzhO0vZ0WpBG1eSIvSxpNJKM324RdYwRuy4SmDRw&e=1773999781"
    },
    {
        "id": "7415",
        "name": "Miami Heat at Houston Rockets (English)",
        "url": "https://mainstreams.pro/hls/bvnsqdfvgha70.m3u8?st=Rle0_jsYNDEJAsJL7FdjBQCEhI7fnLtHLmFTdN1yJ4s&e=1773999781"
    },
    {
        "id": "7416",
        "name": "Indiana Pacers at San Antonio Spurs (English)",
        "url": "https://mainstreams.pro/hls/ztyarueaghj71.m3u8?st=I08uMqOetbVsfOhDGHpHPNA_MfJvoOSHRz984fVwNPY&e=1773999782"
    },
    {
        "id": "7445",
        "name": "Boston Bruins at Detroit Red Wings (English)",
        "url": "https://mainstreams.pro/hls/bvnzadfvyt59.m3u8?st=lWR6DvliP2eH_N2WiLUrXH3qky2_TafNOQjlBhWMpA0&e=1773999782"
    },
    {
        "id": "7442",
        "name": "New York Islanders at Montreal Canadiens (English)",
        "url": "https://mainstreams.pro/hls/poiryezafv56.m3u8?st=BjJFNtKrd6loZcXM7GlBPmcd4ysrCOmQEF_0CjS8130&e=1773999782"
    },
    {
        "id": "7443",
        "name": "Toronto Maple Leafs at Ottawa Senators (English)",
        "url": "https://mainstreams.pro/hls/rzavbdyua57.m3u8?st=4iM0db_vkXZAtiJpgZXJ7h8JGJwE6PVq9F0AaYkOr5o&e=1773999782"
    },
    {
        "id": "7444",
        "name": "St. Louis Blues at Vancouver Canucks (English)",
        "url": "https://mainstreams.pro/hls/earzfddshg58.m3u8?st=Y2WKUQBJaYbOG6QxI3l3xxj-547-WhDuG17hfPqMddY&e=1773999782"
    },
    {
        "id": "7411",
        "name": "Memphis Grizzlies at Charlotte Hornets (English)",
        "url": "https://mainstreams.pro/hls/wfazgsqtrezu66.m3u8?st=l5qeoDBpe_qn14-7sfbi_Rv0S3inTbO_SnX95YtZ1uc&e=1773999782"
    },
    {
        "id": "7412",
        "name": "Los Angeles Lakers at Orlando Magic (English)",
        "url": "https://mainstreams.pro/hls/hfsdqtaxvb67.m3u8?st=KFSHWrBsfoVGsrrolRjdxiL8SgbqmLaLURpgR9j9_Jw&e=1773999783"
    },
    {
        "id": "7413",
        "name": "Cleveland Cavaliers at New Orleans Pelicans (English)",
        "url": "https://mainstreams.pro/hls/zayrtezafgvdv68.m3u8?st=ptwfAeAMfjJonMHYLFzCFbVZIsyGU5iMooVGKcpmXjU&e=1773999783"
    },
    {
        "id": "7410",
        "name": "Oklahoma City Thunder at Washington Wizards (English)",
        "url": "https://mainstreams.pro/hls/mlkijfezag65.m3u8?st=R0DONKxE_BO-9_NKWKjhSHSbg1IYcX3KcIpUiRjv-n8&e=1773999783"
    },
    {
        "id": "7441",
        "name": "Seattle Kraken at Columbus Blue Jackets (English)",
        "url": "https://mainstreams.pro/hls/sdezqfza55.m3u8?st=n2XKfUn7Cinr0d2lO2gUmtuGm8jY25JJg9W-TK8G41Q&e=1773999783"
    },
    {
        "id": "7490",
        "name": "Texas Rangers at Arizona Diamondbacks (English)",
        "url": "https://mainstreams.pro/hls/dzjhkfazbka26.m3u8?st=IC87dYOJnwg1Tj0ZFkRurVyLe8_fpjxC4pzdHQeFkIM&e=1773999783"
    },
    {
        "id": "7491",
        "name": "San Diego Padres at Milwaukee Brewers (English)",
        "url": "https://mainstreams.pro/hls/jzabfazkbf27.m3u8?st=fHtWs090AZSuq3WfEp3HWXd06J2nSn2WBULzh3vm0tw&e=1773999783"
    },
    {
        "id": "7506",
        "name": "Brentford at Leeds United (English)",
        "url": "https://mainstreams.pro/hls/24SDAZFcsqnj24.m3u8?st=-fQjmJqoxVuc30-_Udch6qBWFbrUNeG9pE60UdyzOXU&e=1773999783"
    },
    {
        "id": "7438",
        "name": "Dallas Stars at Minnesota Wild (English)",
        "url": "https://mainstreams.pro/hls/lmdsjkfgv52.m3u8?st=52zLuSCfZQVJ7TssJlP7Pp_UB9whyjsWO0GNKe4Omvk&e=1773999784"
    },
    {
        "id": "7439",
        "name": "Buffalo Sabres at Los Angeles Kings (English)",
        "url": "https://mainstreams.pro/hls/rtzaeyvhb53.m3u8?st=qtYAvT-_lbYtnTwftSHZmHlNv7iAmvKUvjtu1zsPoU0&e=1773999784"
    },
    {
        "id": "7440",
        "name": "Philadelphia Flyers at San Jose Sharks (English)",
        "url": "https://mainstreams.pro/hls/bnvcxwhfg54.m3u8?st=64nDGUwFEJJqzzFFxXluZpx_1R_LflWkTS3a_R-LLBQ&e=1773999784"
    },
    {
        "id": "7512",
        "name": "Valencia at Sevilla (Spanish)",
        "url": "https://mainstreams.pro/hls/377qj1h2727.m3u8?st=3TS2z-DHFXfKoLjHx5Yq4qMz7CN6MfhnluhU3CQMoJE&e=1773999784"
    },
    {
        "id": "7521",
        "name": "Paris Saint-Germain at Nice (English)",
        "url": "https://mainstreams.pro/hls/dza5z8f69.m3u8?st=yOK3PSzylOAGPPWI8u9j716AozSKPoXwnCbAuB3Ee8U&e=1773999784"
    },
    {
        "id": "7517",
        "name": "Sassuolo at Juventus (Italien)",
        "url": "https://mainstreams.pro/hls/syaLqucEne4k.m3u8?st=5ROkBqWbq5jMwlWqDzuV2G_JqG0MkNI1q7DND1jG4v0&e=1773999784"
    },
    {
        "id": "7488",
        "name": "Colorado Rockies at Kansas City Royals (English)",
        "url": "https://mainstreams.pro/hls/fskjanach24.m3u8?st=_fFXKbKE_kRRg1CHJ1Br8h9u9THUjpTzoUFfycd3Fp0&e=1773999785"
    },
    {
        "id": "7489",
        "name": "Cleveland Guardians at San Francisco Giants (English)",
        "url": "https://mainstreams.pro/hls/kjhfzua25.m3u8?st=lTlaalukki1SEdkvWXZqsKsrQjLDMmLgd39SB3-SRDU&e=1773999785"
    },
    {
        "id": "7487",
        "name": "Athletics Athletics at Los Angeles Dodgers (English)",
        "url": "https://mainstreams.pro/hls/jnzkdzjfanch23.m3u8?st=DFNgmyVIdgED1UJGim4JwNU5DNk8JZVzFQvxS7-M0Qk&e=1773999785"
    },
    {
        "id": "7437",
        "name": "Vegas Golden Knights at Nashville Predators (English)",
        "url": "https://mainstreams.pro/hls/hjksgdfauzy51.m3u8?st=TpCQVmzyPAkhT9ashosOGDEzVjJUwJhb_rF-KlInRSg&e=1773999785"
    },
    {
        "id": "7520",
        "name": "Brest at AJ Auxerre (English)",
        "url": "https://mainstreams.pro/hls/dza5z8f69.m3u8?st=VS9vncyZne0LzYzaQfjReFHJXJvkLM-WvpWA1NxOCeY&e=1773999785"
    },
    {
        "id": "7523",
        "name": "Hamburg SV at Borussia Dortmund (Deutch)",
        "url": "https://mainstreams.pro/hls/ueyeztrazb4.m3u8?st=EnYsqFc_-Q10U9n4_ULGW8oDj1pD0tNoaC_579c1pi4&e=1773999785"
    },
    {
        "id": "7505",
        "name": "Chelsea at Everton (English)",
        "url": "https://mainstreams.pro/hls/24SDAZFcsqnj24.m3u8?st=pXAT9OGChsCQufcJPQ43QqaNJZeiM52pNNn9LjVyq9g&e=1773999786"
    },
    {
        "id": "7510",
        "name": "Girona at Osasuna (Spanish)",
        "url": "https://mainstreams.pro/hls/377qj1h2727.m3u8?st=j5NAOGqaYayHtfEydyxW4fkDw3HXELUuJ8Ha3wDwcpg&e=1773999786"
    },
    {
        "id": "7511",
        "name": "Real Oviedo at Levante (Spanish)",
        "url": "https://mainstreams.pro/hls/griogoehvn2.m3u8?st=Yn2e0Ap4xE5oIJbKOYBnJsZtyq1stc0_ngPt4EuJ3Wc&e=1773999786"
    },
    {
        "id": "7486",
        "name": "Houston Astros at New York Mets (English)",
        "url": "https://mainstreams.pro/hls/ijfnakfidch22.m3u8?st=Mo9x-xmdKq8PkLpaVcgAYDgT4jdhVpstYQ53OH3KlBk&e=1773999786"
    },
    {
        "id": "7479",
        "name": "Philadelphia Phillies at Baltimore Orioles (English)",
        "url": "https://mainstreams.pro/hls/dazhfiach15.m3u8?st=hK9_Ai3F_NQqra8NB3KU2qYFZGvicmHdsEk-8-UDD78&e=1773999786"
    },
    {
        "id": "7480",
        "name": "Atlanta Braves at Boston Red Sox (English)",
        "url": "https://mainstreams.pro/hls/16yuitzaerghbhc16.m3u8?st=yNmU2TVlasg6llZTbhRVbbXHU3xVFClw5H1f00l1094&e=1773999786"
    },
    {
        "id": "7481",
        "name": "New York Yankees at Detroit Tigers (English)",
        "url": "https://mainstreams.pro/hls/ihfazugfyjcazich17.m3u8?st=YcTyu_phW-1A8IHn7hl6J1NPVKDmqA3ItU2LzkjO1LI&e=1773999787"
    },
    {
        "id": "7482",
        "name": "Toronto Blue Jays at Pittsburgh Pirates (English)",
        "url": "https://mainstreams.pro/hls/Czajafjihafch18.m3u8?st=jvDgLYB8TGxxzYqOz4u8CcRFFBHs8sDHv-To_B1gBtg&e=1773999787"
    },
    {
        "id": "7483",
        "name": "Miami Marlins at St. Louis Cardinals (English)",
        "url": "https://mainstreams.pro/hls/bzagLHzach19.m3u8?st=y0GUpybpGtqQK4sdRWJ4laIYlwU99RyA0EPoGLXnknQ&e=1773999787"
    },
    {
        "id": "7484",
        "name": "Minnesota Twins at Tampa Bay Rays (English)",
        "url": "https://mainstreams.pro/hls/jkzahzadach20.m3u8?st=Uq6KjJd7xFBUTqAkiUQqfG5tAQJhabMxqlVphZFKIeQ&e=1773999787"
    },
    {
        "id": "7485",
        "name": "New York Mets at Washington Nationals (English)",
        "url": "https://mainstreams.pro/hls/ojzkajnach21.m3u8?st=rS-Apr9BHGDQ8NwqG9sYBtQK8R5OyTQknOiO_jE0U9M&e=1773999787"
    },
    {
        "id": "7436",
        "name": "Winnipeg Jets at Pittsburgh Penguins (English)",
        "url": "https://mainstreams.pro/hls/uyopzarf50.m3u8?st=OhjiHSBEO1S0KFquB19_I0KJuGJMORUNokNqe3HKRDQ&e=1773999787"
    },
    {
        "id": "7447",
        "name": "UFC Fight Night: Evloev vs. Murphy (English)",
        "url": "https://mainstreams.pro/hls/zeuryuegn48.m3u8?st=uW-_3RzGXGtEkJElWm3RGusZhBjDSoVgbUmfIbMzDfo&e=1773999788"
    },
    {
        "id": "7516",
        "name": "Torino at AC Milan (Italien)",
        "url": "https://mainstreams.pro/hls/syaLqucEne4k.m3u8?st=vBLoNC2Zuril_ciuBy3DTujhiilucv38FEwop1y_2ow&e=1773999788"
    },
    {
        "id": "7519",
        "name": "Lorient at Toulouse (English)",
        "url": "https://mainstreams.pro/hls/dza5z8f69.m3u8?st=mwqlCOfVsU8yWP6sVrjSX8ysspC0C_loRke3EYC-Z4E&e=1773999788"
    },
    {
        "id": "7509",
        "name": "Getafe at Espanyol (English)",
        "url": "https://mainstreams.pro/hls/377qj1h2727.m3u8?st=rbDet9SrIekGNoiV9h3qrdZQq14sZA5W3NTzWBXeP7Y&e=1773999788"
    },
    {
        "id": "7504",
        "name": "Burnley at Fulham (English)",
        "url": "https://mainstreams.pro/hls/24SDAZFcsqnj24.m3u8?st=xwk9jbXN14qm_pBNPnqXWhj1D7jhTlSbkrOwlZtSRxE&e=1773999788"
    },
    {
        "id": "7522",
        "name": "1. FC Union Berlin at Bayern Munich (Deutch)",
        "url": "https://mainstreams.pro/hls/ueyeztrazb4.m3u8?st=ztB7if81p3DFeXlZOtfO7_7lCPJFpqMfJ_XvZNDeE8I&e=1773999788"
    },
    {
        "id": "7515",
        "name": "Cremonese at Parma (Italien)",
        "url": "https://mainstreams.pro/hls/syaLqucEne4k.m3u8?st=bsCCCojyEhnW4Trm-xM0w4vWbTQMHJedoT0dXriAeso&e=1773999789"
    },
    {
        "id": "7508",
        "name": "Mallorca at Elche (English)",
        "url": "https://mainstreams.pro/hls/377qj1h2727.m3u8?st=qLgskswzHoKvsQp_PJsAonEPQIk9ASB8NpfaD__p2Ls&e=1773999789"
    },
    {
        "id": "7503",
        "name": "Liverpool at Brighton & Hove Albion (English)",
        "url": "https://mainstreams.pro/hls/24SDAZFcsqnj24.m3u8?st=aGSmWBQn5d4ycEqpSTE24ZWFn4Ti9oqhSBIsllYswx0&e=1773999789"
    },
    {
        "id": "7435",
        "name": "Anaheim Ducks at Utah Mammoth (English)",
        "url": "https://mainstreams.pro/hls/bnvcxwhfg54.m3u8?st=e29_kQf9Nss2BuQYJ-eb-bfnCWM_qzmvVVRUoa2W_k8&e=1773999789"
    },
    {
        "id": "7477",
        "name": "Chicago Cubs at Athletics Athletics (English)",
        "url": "https://mainstreams.pro/hls/JHDAJBDnjdna30.m3u8?st=-Ll4TRFXfN8NMMDApY7keOi57YNUDfg9BoCXEjvc_Q0&e=1773999789"
    },
    {
        "id": "7478",
        "name": "Colorado Rockies at San Diego Padres (English)",
        "url": "https://mainstreams.pro/hls/sfjnzabacah31.m3u8?st=rU7p3K1zaQmJ78dINTfl0oVNzlQoM2lbei1qc1B7ze0&e=1773999789"
    },
    {
        "id": "7473",
        "name": "Cincinnati Reds at Chicago Cubs (English)",
        "url": "https://mainstreams.pro/hls/dzjhkfazbka26.m3u8?st=qvHOmNw8D8jKfggl_57YPd4zbzNLEFdeEILuGVvZ0lc&e=1773999789"
    },
    {
        "id": "7474",
        "name": "Seattle Mariners at Cleveland Guardians (English)",
        "url": "https://mainstreams.pro/hls/jzabfazkbf27.m3u8?st=g1lxFpGCZXwNsDDhlOW1M2x6MavMVn0ZZEL8FHoi0iY&e=1773999790"
    },
    {
        "id": "7475",
        "name": "San Diego Padres at Los Angeles Dodgers (English)",
        "url": "https://mainstreams.pro/hls/hefbafbakx28.m3u8?st=jUAbNU-Sjvl3McNz3c_M4s-gZJEOjf01N9XHoW7J4gc&e=1773999790"
    },
    {
        "id": "7476",
        "name": "San Francisco Giants at Texas Rangers (English)",
        "url": "https://mainstreams.pro/hls/hfzljfahzcax29.m3u8?st=BrKF0msI04Dgs-B9aL3ZP4pVRygNBm4Gy3ZkDU2Y2cU&e=1773999790"
    },
    {
        "id": "7409",
        "name": "Toronto Raptors at Denver Nuggets (English)",
        "url": "https://mainstreams.pro/hls/bvnsqdfvgha70.m3u8?st=hHNbDGMXeHEt6rWKF7BzBn4zLY_r8DV9oyshkLbb4J4&e=1773999790"
    },
    {
        "id": "7434",
        "name": "Florida Panthers at Calgary Flames (English)",
        "url": "https://mainstreams.pro/hls/rtzaeyvhb53.m3u8?st=2nb0pmnVBUFJOOPnf3R5VW8TQTDYlFne1VnliahIt7c&e=1773999790"
    },
    {
        "id": "7433",
        "name": "Colorado Avalanche at Chicago Blackhawks (English)",
        "url": "https://mainstreams.pro/hls/lmdsjkfgv52.m3u8?st=WfRA5fdJq6ENXM91Bp3USf8N6akonfe35FFSubIG6mk&e=1773999790"
    },
    {
        "id": "7472",
        "name": "Kansas City Royals at San Francisco Giants (English)",
        "url": "https://mainstreams.pro/hls/kjhfzua25.m3u8?st=kbmKmiJ4KENrnHZdYw660al4aVE7KCL-GS6uBbcJg1s&e=1773999790"
    },
    {
        "id": "7406",
        "name": "Atlanta Hawks at Houston Rockets (English)",
        "url": "https://mainstreams.pro/hls/hfsdqtaxvb67.m3u8?st=xsrGQZZuUuAWaP1FDBr5gkACYjm6iu8n_hWVzOkBGEA&e=1773999791"
    },
    {
        "id": "7407",
        "name": "Boston Celtics at Memphis Grizzlies (English)",
        "url": "https://mainstreams.pro/hls/zayrtezafgvdv68.m3u8?st=MeWEcX2eo1-5Haact7CKnrt-Ay-aPtH6dJDATmdtO4c&e=1773999791"
    },
    {
        "id": "7408",
        "name": "Portland Trail Blazers at Minnesota Timberwolves (English)",
        "url": "https://mainstreams.pro/hls/zeafwqvhfe69.m3u8?st=YLpQPiGkU0pc6SDJ73LG4Ihp7YAkTyPjtLlbiiF3nso&e=1773999791"
    },
    {
        "id": "7404",
        "name": "New York Knicks at Brooklyn Nets (English)",
        "url": "https://mainstreams.pro/hls/mlkijfezag65.m3u8?st=bBoz6vOVamUI2gD9bZw6zPXXRgVH4H-ZJzMhm94Gq3o&e=1773999791"
    },
    {
        "id": "7405",
        "name": "Golden State Warriors at Detroit Pistons (English)",
        "url": "https://mainstreams.pro/hls/wfazgsqtrezu66.m3u8?st=7Km1rSdTmjxGHak9rCo1aJ5lytbcqqSwr6I0yACaseI&e=1773999791"
    },
    {
        "id": "7471",
        "name": "Washington Nationals at Miami Marlins (English)",
        "url": "https://mainstreams.pro/hls/fskjanach24.m3u8?st=cBQYBnTCW8rLZgVeyq2Zrm_PHr5wtIhA9r5XfkKPMNc&e=1773999791"
    },
    {
        "id": "7431",
        "name": "Carolina Hurricanes at Toronto Maple Leafs (English)",
        "url": "https://mainstreams.pro/hls/uyopzarf50.m3u8?st=oMJ3A55Zwpj1NvJqLef2U17bowHDpvQzRolxCxzfxN0&e=1773999792"
    },
    {
        "id": "7432",
        "name": "New Jersey Devils at Washington Capitals (English)",
        "url": "https://mainstreams.pro/hls/hjksgdfauzy51.m3u8?st=-GWwjaTUIpxGDmlJ-6vCuoKZsOattdhAH8bjb8pIuZE&e=1773999792"
    },
    {
        "id": "7470",
        "name": "Baltimore Orioles at New York Yankees (English)",
        "url": "https://mainstreams.pro/hls/jnzkdzjfanch23.m3u8?st=vAqTo9M9olaeVpvH67PHtgNSrDyqTU-tDIHI8l6elaU&e=1773999792"
    },
    {
        "id": "7468",
        "name": "Pittsburgh Pirates at Atlanta Braves (English)",
        "url": "https://mainstreams.pro/hls/ojzkajnach21.m3u8?st=kbrN88Lh-XH7_TG-JhXeOL-dw40Ml8h5aoKvJwUdjEA&e=1773999792"
    },
    {
        "id": "7469",
        "name": "Miami Marlins at Houston Astros (English)",
        "url": "https://mainstreams.pro/hls/ijfnakfidch22.m3u8?st=F7PyjV9ptLV0FiWN-YoxP5pISSFxvN7U0shRv2uB04Y&e=1773999792"
    },
    {
        "id": "7467",
        "name": "Milwaukee Brewers at Arizona Diamondbacks (English)",
        "url": "https://mainstreams.pro/hls/jkzahzadach20.m3u8?st=94iWKtrXJ6mVAUXileFjzoDseHDSQF5jXJ_hhOPUne0&e=1773999792"
    },
    {
        "id": "7507",
        "name": "Real Sociedad at Villarreal (English)",
        "url": "https://mainstreams.pro/hls/377qj1h2727.m3u8?st=s3Xi6Kf485UidSFhy2p1eDSPL3rrsBTD4q-rQp_3214&e=1773999792"
    },
    {
        "id": "7502",
        "name": "Manchester United at AFC Bournemouth (English)",
        "url": "https://mainstreams.pro/hls/24SDAZFcsqnj24.m3u8?st=zNZKeQaxJWEhSOwDWE_wr_gR5ifgnevNF4dPneEksXY&e=1773999793"
    },
    {
        "id": "7518",
        "name": "Angers at Lens (English)",
        "url": "https://mainstreams.pro/hls/dza5z8f69.m3u8?st=h9xj_vO5TqVrRZYGk-oFmhnca35koG9kW9nSX_BO3g0&e=1773999793"
    },
    {
        "id": "7514",
        "name": "Udinese at Genoa (Italien)",
        "url": "https://mainstreams.pro/hls/syaLqucEne4k.m3u8?st=1TLecHQgzukd4rQj8C9MnTwfwa4DtCxngSVjs-3U18A&e=1773999793"
    },
    {
        "id": "7466",
        "name": "Chicago White Sox at Los Angeles Angels (English)",
        "url": "https://mainstreams.pro/hls/bzagLHzach19.m3u8?st=2dsYGyd3LhVJY3JhQxTuof7RBKd9H1UiCslrWMw5C-U&e=1773999793"
    },
    {
        "id": "7513",
        "name": "Napoli at Cagliari (Italien)",
        "url": "https://mainstreams.pro/hls/syaLqucEne4k.m3u8?st=1TLecHQgzukd4rQj8C9MnTwfwa4DtCxngSVjs-3U18A&e=1773999793"
    },
    {
        "id": "7465",
        "name": "St. Louis Cardinals at New York Mets (English)",
        "url": "https://mainstreams.pro/hls/Czajafjihafch18.m3u8?st=QqP8d7yZ9wKqcObAtG4hRuqHRihBiDKh4PrMf1Q89Zs&e=1773999793"
    },
    {
        "id": "7462",
        "name": "Toronto Blue Jays at Minnesota Twins (English)",
        "url": "https://mainstreams.pro/hls/dazhfiach15.m3u8?st=ypJBhNrwNhS74rN7vhRg__T3nu7NmuL3s_IioMOCrFg&e=1773999794"
    },
    {
        "id": "7463",
        "name": "Detroit Tigers at Philadelphia Phillies (English)",
        "url": "https://mainstreams.pro/hls/16yuitzaerghbhc16.m3u8?st=iHDwkpcyrd_q2fqmaHto5EgkQc97EQfB24kvagoyDIM&e=1773999794"
    },
    {
        "id": "7464",
        "name": "Boston Red Sox at Tampa Bay Rays (English)",
        "url": "https://mainstreams.pro/hls/ihfazugfyjcazich17.m3u8?st=k4YpQTT9hdvnfVsx1_HcHhUpmaYMaa8oMBNHkgmXf9A&e=1773999794"
    }
]