[
    {
        "id": "8571",
        "name": "Celta Vigo at Barcelona (Spanish)",
        "url": "https://mainstreams.pro/hls/377qj1h2727.m3u8?st=QK04PrR35kNfERCS9QxPpV7a3zng8gvK4e5KDVMkd2U&e=1776714947"
    },
    {
        "id": "8568",
        "name": "Nice at Strasbourg (English)",
        "url": "https://mainstreams.pro/hls/dza5z8f69.m3u8?st=_KkMzFwuY2umUiOAdKzY2_K3_MJOmVxsv3Jy_mGOp5s&e=1776714947"
    },
    {
        "id": "8569",
        "name": "Manchester City at Burnley (English)",
        "url": "https://mainstreams.pro/hls/24SDAZFcsqnj24.m3u8?st=Taxd6EmWXtc9fBcvWHUQ-vSEb9jFeRvHCoqsFa304v0&e=1776714947"
    },
    {
        "id": "8570",
        "name": "Leeds United at AFC Bournemouth (English)",
        "url": "https://mainstreams.pro/hls/eJmauBDCIf.m3u8?st=PkYsYzIDppV00oRPIrvwkHtiW1m0kn7sv5CY1nk3rLs&e=1776714947"
    },
    {
        "id": "8562",
        "name": "Lazio at Atalanta (Italien)",
        "url": "https://mainstreams.pro/hls/syaLqucEne4k.m3u8?st=sXtpqfws4-NWJKDoLhlmpi3zOJ1yAooMMC7qPGyhtbM&e=1776714947"
    },
    {
        "id": "8575",
        "name": "Bayern Munich at Bayer Leverkusen (English)",
        "url": "https://mainstreams.pro/hls/ueyeztrazb4.m3u8?st=b4sF47TpFAJ4OAZu9eYEjOJZ4_ZC8zU0LTNZXCWgEag&e=1776714947"
    },
    {
        "id": "8573",
        "name": "Getafe at Real Sociedad (Spanish)",
        "url": "https://mainstreams.pro/hls/b0h5fNwDKH.m3u8?st=h4Mzjq7r85Gk9NrkotCdu22kdZ_KvnV2Wxp3mZTdduc&e=1776714948"
    },
    {
        "id": "8574",
        "name": "Nantes at Paris Saint-Germain (English)",
        "url": "https://mainstreams.pro/hls/dza5z8f69.m3u8?st=2X7d9spUBndxfPG8BkGzHnHWf3jRGDmVMhXADPzZ0ok&e=1776714948"
    },
    {
        "id": "8572",
        "name": "Atl\u00e9tico Madrid at Elche (Spanish)",
        "url": "https://mainstreams.pro/hls/377qj1h2727.m3u8?st=UuLFLQNVT9pEZ9DObi2Lwtbxj-M6AgKyWGC0EUr2J14&e=1776714948"
    },
    {
        "id": "8566",
        "name": "Real Betis at Girona (Spanish)",
        "url": "https://mainstreams.pro/hls/griogoehvn2.m3u8?st=NAldzXHNI9_6ftVoWeGh65aMjHp6dsHuSgDEkrKewYo&e=1776714948"
    },
    {
        "id": "8564",
        "name": "Alav\u00e9s at Real Madrid (Spanish)",
        "url": "https://mainstreams.pro/hls/377qj1h2727.m3u8?st=UuLFLQNVT9pEZ9DObi2Lwtbxj-M6AgKyWGC0EUr2J14&e=1776714948"
    },
    {
        "id": "8567",
        "name": "Toulouse at Lens (English)",
        "url": "https://mainstreams.pro/hls/dza5z8f69.m3u8?st=2X7d9spUBndxfPG8BkGzHnHWf3jRGDmVMhXADPzZ0ok&e=1776714948"
    },
    {
        "id": "8560",
        "name": "Chelsea at Brighton & Hove Albion (English)",
        "url": "https://mainstreams.pro/hls/24SDAZFcsqnj24.m3u8?st=4W6V3_ToD9lVGEgBIWVz5JvxrfxOAoiMqDaki2CSrfg&e=1776714949"
    },
    {
        "id": "8561",
        "name": "Como at Internazionale (Italien)",
        "url": "https://mainstreams.pro/hls/syaLqucEne4k.m3u8?st=9XXdz2P1k5BZPZdP2g5TWxeswDBLgwoNT-fXdzKNQF4&e=1776714949"
    },
    {
        "id": "8565",
        "name": "Valencia at Mallorca (Spanish)",
        "url": "https://mainstreams.pro/hls/griogoehvn2.m3u8?st=PN9tiyY9admKgvT96rPQdW3ylZLOasYoWXlYnlMQ9Pw&e=1776714949"
    },
    {
        "id": "8563",
        "name": "Osasuna at Athletic Club (Spain)",
        "url": "https://mainstreams.pro/hls/377qj1h2727.m3u8?st=U-tl2D2Moe_sV4MP_ro89gWfezajV4ymQrWzvAuKwEM&e=1776714949"
    },
    {
        "id": "8578",
        "name": "Minnesota Timberwolves at Denver Nuggets (English)",
        "url": "https://mainstreams.pro/hls/hfsdqtaxvb67.m3u8?st=BORYw3rt7wbtWrxws8wjQkF1yaYDPkF4TEC1jSk50L8&e=1776714949"
    },
    {
        "id": "8582",
        "name": "Anaheim Ducks at Edmonton Oilers (English)",
        "url": "https://mainstreams.pro/hls/rtzaeyvhb53.m3u8?st=raMlqcQBBDmanf2gcW2yrkp3VwwzVUB-EDKH-DhUGEM&e=1776714949"
    },
    {
        "id": "8592",
        "name": "Athletics Athletics at Seattle Mariners (English)",
        "url": "https://mainstreams.pro/hls/fskjanach24.m3u8?st=afeUnZdMWHjtyv4o121CRadyFsThH5ATSRW_2HLWrxY&e=1776714950"
    },
    {
        "id": "8591",
        "name": "Toronto Blue Jays at Los Angeles Angels (English)",
        "url": "https://mainstreams.pro/hls/jnzkdzjfanch23.m3u8?st=YCpyXmtp4y8WBmEqNOy-60ZiL_8rDvxezufBsz0uw3E&e=1776714950"
    },
    {
        "id": "8581",
        "name": "Minnesota Wild at Dallas Stars (English)",
        "url": "https://mainstreams.pro/hls/lmdsjkfgv52.m3u8?st=yW_1Zpy--5DQlJic6U2SNQ8pb5D51HRTGc1hrwAr7Rc&e=1776714950"
    },
    {
        "id": "8590",
        "name": "Los Angeles Dodgers at Colorado Rockies (English)",
        "url": "https://mainstreams.pro/hls/ijfnakfidch22.m3u8?st=AI69xJmA5mLl3Y0tRoDtxyJysUU6SgW6BfXWshvgVW0&e=1776714950"
    },
    {
        "id": "8577",
        "name": "Atlanta Hawks at New York Knicks (English)",
        "url": "https://mainstreams.pro/hls/wfazgsqtrezu66.m3u8?st=kA3mxmTV82SztBc1KnjMsGQOB0IlyVokkQu8Q59od6g&e=1776714950"
    },
    {
        "id": "8588",
        "name": "Baltimore Orioles at Kansas City Royals (English)",
        "url": "https://mainstreams.pro/hls/jkzahzadach20.m3u8?st=LnbDhgVnyo--encGfNs4Tv3m1RidTWJ-0rR092ecTvU&e=1776714950"
    },
    {
        "id": "8589",
        "name": "Philadelphia Phillies at Chicago Cubs (English)",
        "url": "https://mainstreams.pro/hls/ojzkajnach21.m3u8?st=IZiiXSkIvJu8df__C240lKtpHTRBjxtgaDor9D06SVI&e=1776714950"
    },
    {
        "id": "8580",
        "name": "Ottawa Senators at Carolina Hurricanes (English)",
        "url": "https://mainstreams.pro/hls/hjksgdfauzy51.m3u8?st=SieuTcIBc7mfXX9kU5lFIvyjN24rj2HIUGg5K5Uij1k&e=1776714950"
    },
    {
        "id": "8579",
        "name": "Philadelphia Flyers at Pittsburgh Penguins (English)",
        "url": "https://mainstreams.pro/hls/uyopzarf50.m3u8?st=48RqNHj4JBIx1CgNp95x7gzFlZADInLgWRWA4arxyyM&e=1776714950"
    },
    {
        "id": "8576",
        "name": "Toronto Raptors at Cleveland Cavaliers (English)",
        "url": "https://mainstreams.pro/hls/mlkijfezag65.m3u8?st=VwsobZl3r_voZehjOut1sn7CYw90_oqVi7d-ikoxMEU&e=1776714951"
    },
    {
        "id": "8587",
        "name": "Atlanta Braves at Washington Nationals (English)",
        "url": "https://mainstreams.pro/hls/bzagLHzach19.m3u8?st=SvJaIH2EAm4lJ29wceY_Wxbb1q-VkAzooxWjwQzflkM&e=1776714951"
    },
    {
        "id": "8585",
        "name": "Cincinnati Reds at Tampa Bay Rays (English)",
        "url": "https://mainstreams.pro/hls/ihfazugfyjcazich17.m3u8?st=7fg7cHHCXOwnvgaO2S8Kgr0KCyJXqxw05-pz4cvLmlE&e=1776714951"
    },
    {
        "id": "8586",
        "name": "St. Louis Cardinals at Miami Marlins (English)",
        "url": "https://mainstreams.pro/hls/Czajafjihafch18.m3u8?st=U__s0-x1Sr1PidYJFIAQLG1pmV5x6Py-udhKSH03OQs&e=1776714951"
    },
    {
        "id": "8584",
        "name": "Houston Astros at Cleveland Guardians (English)",
        "url": "https://mainstreams.pro/hls/16yuitzaerghbhc16.m3u8?st=R32n8g_Zc8jKjX7SHEdjfXdWRRK0yszk4g7TvdFwW6I&e=1776714951"
    },
    {
        "id": "8558",
        "name": "West Ham United at Crystal Palace (English)",
        "url": "https://mainstreams.pro/hls/24SDAZFcsqnj24.m3u8?st=EoIvC-Z-acdmCVed7H4j923B-5waEnKQ_au5dqUWmDQ&e=1776714951"
    },
    {
        "id": "8559",
        "name": "Fiorentina at Lecce (Italien)",
        "url": "https://mainstreams.pro/hls/syaLqucEne4k.m3u8?st=8Nuv-LsxSBPKDf-DHlZTUEMg3_wUBRSL0xRVf7XXVXY&e=1776714952"
    },
    {
        "id": "8583",
        "name": "Detroit Tigers at Boston Red Sox (English)",
        "url": "https://mainstreams.pro/hls/dazhfiach15.m3u8?st=AE3cmc1NTSpY1t2C2IZPropOwRg6TTwVNO1d-d2n4Eg&e=1776714952"
    }
]