[
    {
        "id": "7643",
        "name": "Toronto Raptors at LA Clippers (English)",
        "url": "https://mainstreams.pro/hls/xcsfadafgzfg76.m3u8?st=59KdMpuOhuCM-PsIEj2wq1rXA-Nm39Ng66mKFqT_RS0&e=1774481417"
    },
    {
        "id": "7640",
        "name": "Dallas Mavericks at Denver Nuggets (English)",
        "url": "https://mainstreams.pro/hls/fdgsqdfawa73.m3u8?st=2ft1-Qb9YLnAJ1ykW3u4R-K2uz0Bdzk0LVTAG5wvY90&e=1774481417"
    },
    {
        "id": "7641",
        "name": "Brooklyn Nets at Golden State Warriors (English)",
        "url": "https://mainstreams.pro/hls/yjtzafghvjza74.m3u8?st=v8zXL3lHI-j_mdRxfFfPi0rMuBt8xPyzWdk94QPlo2g&e=1774481417"
    },
    {
        "id": "7642",
        "name": "Milwaukee Bucks at Portland Trail Blazers (English)",
        "url": "https://mainstreams.pro/hls/sqhdghzavbxu75.m3u8?st=sqpCb4UUY7MxKdw81Ap_5OgCIDmQfFIGMH4Kgh_VDdg&e=1774481418"
    },
    {
        "id": "7639",
        "name": "Houston Rockets at Minnesota Timberwolves (English)",
        "url": "https://mainstreams.pro/hls/pllmazjkdzajh72.m3u8?st=ryYcDEebmBti8aOpAbyzyByNqJemBFagC6atFtPGjYk&e=1774481418"
    },
    {
        "id": "7648",
        "name": "None (English)",
        "url": "https://mainstreams.pro/hls/rteztryzathc77.m3u8?st=mboOlR0NvVrWUI-10y18gfmmllyUy7UDTa9S3Ad-UOE&e=1774481418"
    },
    {
        "id": "7638",
        "name": "Washington Wizards at Utah Jazz (English)",
        "url": "https://mainstreams.pro/hls/ztyarueaghj71.m3u8?st=Tmii_oLR7RnKJfR6-biTtAGFRDfsvvAty439PnA34n4&e=1774481418"
    },
    {
        "id": "7644",
        "name": "New York Yankees at San Francisco Giants (English)",
        "url": "https://mainstreams.pro/hls/dazhfiach15.m3u8?st=-3xfPcUVp1lFdJ-Q9_9PSjfOOZ4wq5O1B8ws4oA0Phc&e=1774481418"
    },
    {
        "id": "7637",
        "name": "San Antonio Spurs at Memphis Grizzlies (English)",
        "url": "https://mainstreams.pro/hls/bvnsqdfvgha70.m3u8?st=xuIKTkBuffcGbWmbi53BbR89zLZ73WzVN7RyZqlQFEg&e=1774481418"
    },
    {
        "id": "7635",
        "name": "Oklahoma City Thunder at Boston Celtics (English)",
        "url": "https://mainstreams.pro/hls/zayrtezafgvdv68.m3u8?st=-J2Ay65I1O-JexJnix2-90QoFBO55EqyOrj22Hk9aDk&e=1774481418"
    },
    {
        "id": "7636",
        "name": "Miami Heat at Cleveland Cavaliers (English)",
        "url": "https://mainstreams.pro/hls/zeafwqvhfe69.m3u8?st=LDVlp-ibjG4uq6LWhWLOWVVPXMnxJeJP4iy8TIStpWY&e=1774481418"
    },
    {
        "id": "7645",
        "name": "Boston Bruins at Buffalo Sabres (English)",
        "url": "https://mainstreams.pro/hls/uyopzarf50.m3u8?st=YVoBFmJzLlfCdjKoEk5_jMvScgKOL7RPGHbx2e3Oeug&e=1774481418"
    },
    {
        "id": "7646",
        "name": "New York Rangers at Toronto Maple Leafs (English)",
        "url": "https://mainstreams.pro/hls/hjksgdfauzy51.m3u8?st=w5e-y_VRgUlruZdMXMLr7wSxHeHfZbh3apvoQ5CJXOQ&e=1774481419"
    },
    {
        "id": "7647",
        "name": "None (English)",
        "url": "https://mainstreams.pro/hls/rteztryzathc77.m3u8?st=lWCBRE5D-kG0fzlzGFy0DZUxU5IcTLgmEhGkjFN0m6E&e=1774481419"
    },
    {
        "id": "7632",
        "name": "Atlanta Hawks at Detroit Pistons (English)",
        "url": "https://mainstreams.pro/hls/mlkijfezag65.m3u8?st=OoufWqvpkZNHvAMumS9kiHNAr-qLPwsaaKfRW53LEoo&e=1774481419"
    },
    {
        "id": "7633",
        "name": "Los Angeles Lakers at Indiana Pacers (English)",
        "url": "https://mainstreams.pro/hls/wfazgsqtrezu66.m3u8?st=sGI0gATGkLKD0h3becMgtCNhhFXKUQmWlw3V8iIjXqA&e=1774481419"
    },
    {
        "id": "7634",
        "name": "Chicago Bulls at Philadelphia 76ers (English)",
        "url": "https://mainstreams.pro/hls/hfsdqtaxvb67.m3u8?st=3g2EKvYYMrxI1nnimVUq-1NgKpY03EuryeOBnGi66kQ&e=1774481419"
    }
]