[
    {
        "id": "7227",
        "name": "Utah Jazz at Sacramento Kings (English)",
        "url": "https://mainstreams.pro/hls/ztyarueaghj71.m3u8?st=7fqRvQfL7bMhVO00dki4dU8uJ6HED2Rl5Rs1OubgsTc&e=1773627647"
    },
    {
        "id": "7246",
        "name": "Nashville Predators at Edmonton Oilers (English)",
        "url": "https://mainstreams.pro/hls/bnvcxwhfg54.m3u8?st=pc47WuzJZZg7SftkARrIjxBIAWpHUPASrSppuzebaU4&e=1773627647"
    },
    {
        "id": "7247",
        "name": "Florida Panthers at Seattle Kraken (English)",
        "url": "https://mainstreams.pro/hls/sdezqfza55.m3u8?st=cE-A5_UGBpJHr0q-LF4qeUQdXRiqmzZO14DwTyajCzo&e=1773627647"
    },
    {
        "id": "7226",
        "name": "Golden State Warriors at New York Knicks (English)",
        "url": "https://mainstreams.pro/hls/bvnsqdfvgha70.m3u8?st=qQ0oscVEj-5zC0-pYT2Csvoh6lPKpD0QAuY4ggJiViA&e=1773627648"
    },
    {
        "id": "7245",
        "name": "Toronto Maple Leafs at Minnesota Wild (English)",
        "url": "https://mainstreams.pro/hls/rtzaeyvhb53.m3u8?st=86F2Vlayj3gu2gKUAKKNsWD_T1Ig6MEsJBut7VIteDs&e=1773627648"
    },
    {
        "id": "7244",
        "name": "Anaheim Ducks at Montreal Canadiens (English)",
        "url": "https://mainstreams.pro/hls/lmdsjkfgv52.m3u8?st=CQX7ribVRBF1310h2XoXJ8_2cjYQbar4y7O_mf2oRo8&e=1773627648"
    },
    {
        "id": "7297",
        "name": "New York Yankees at Baltimore Orioles (English)",
        "url": "https://mainstreams.pro/hls/JHDAJBDnjdna30.m3u8?st=vePAZ2Srkt0rRHqtfqZquiUtDxAg1IPF5KB0wnVQDbQ&e=1773627648"
    },
    {
        "id": "7225",
        "name": "Portland Trail Blazers at Philadelphia 76ers (English)",
        "url": "https://mainstreams.pro/hls/zeafwqvhfe69.m3u8?st=NFwLAL1FEwWoQVnBAqrGl4x1YB1XerQv7RtPfmcuUvM&e=1773627648"
    },
    {
        "id": "7243",
        "name": "San Jose Sharks at Ottawa Senators (English)",
        "url": "https://mainstreams.pro/hls/hjksgdfauzy51.m3u8?st=6xuDqdWQLTG5Y0enY18htgVteCI4B0y7CCVEQ7sw27A&e=1773627648"
    },
    {
        "id": "7294",
        "name": "San Diego Padres at Arizona Diamondbacks (English)",
        "url": "https://mainstreams.pro/hls/jzabfazkbf27.m3u8?st=Wyrih0EnsfHst78MFw1yguXQQyElgYwOYtSRawJWv0Q&e=1773627649"
    },
    {
        "id": "7295",
        "name": "Colorado Rockies at Los Angeles Angels (English)",
        "url": "https://mainstreams.pro/hls/hefbafbakx28.m3u8?st=HwcDXxTI_JWwtiOS4wE-dUxaJa-hRh2ff27wTcohY18&e=1773627649"
    },
    {
        "id": "7296",
        "name": "Cincinnati Reds at Seattle Mariners (English)",
        "url": "https://mainstreams.pro/hls/hfzljfahzcax29.m3u8?st=T5TLH298L8t_ZuAX08wO3v0fqbBhTK4dsCskIUZ7Itk&e=1773627649"
    },
    {
        "id": "7289",
        "name": "Los Angeles Dodgers at Chicago Cubs (English)",
        "url": "https://mainstreams.pro/hls/ijfnakfidch22.m3u8?st=5BS18VeNcvhH5zjkGm55kvBMzOQdNZdFR8qP5ib5r3I&e=1773627649"
    },
    {
        "id": "7290",
        "name": "Athletics Athletics at Cleveland Guardians (English)",
        "url": "https://mainstreams.pro/hls/jnzkdzjfanch23.m3u8?st=uaGigxWjz05qkdu_V0mEtPtgVfTl02pDzAvDZJ_Leso&e=1773627649"
    },
    {
        "id": "7291",
        "name": "Chicago White Sox at Kansas City Royals (English)",
        "url": "https://mainstreams.pro/hls/fskjanach24.m3u8?st=Lx2PEVYIT5RkmwZXzJrDPpJ86JP8_n1JlvOZccj2iLg&e=1773627649"
    },
    {
        "id": "7292",
        "name": "Texas Rangers at Los Angeles Dodgers (English)",
        "url": "https://mainstreams.pro/hls/kjhfzua25.m3u8?st=8hZPuDKqr-XPPNJss6PywqihrWgZt7ErRA00LdoLXlw&e=1773627650"
    },
    {
        "id": "7293",
        "name": "Milwaukee Brewers at San Francisco Giants (English)",
        "url": "https://mainstreams.pro/hls/dzjhkfazbka26.m3u8?st=VWiqgC56_J5tWl9YwK4Wun43lToqDEmwXQyaVkPQ2cQ&e=1773627650"
    },
    {
        "id": "7196",
        "name": "Osasuna at Real Sociedad (Spanish)",
        "url": "https://mainstreams.pro/hls/377qj1h2727.m3u8?st=bdYkdntYV2SlkldZ8dz2Fs5VpjKpLy57ylUxcqyyqIU&e=1773627650"
    },
    {
        "id": "7204",
        "name": "AC Milan at Lazio (Italien)",
        "url": "https://mainstreams.pro/hls/syaLqucEne4k.m3u8?st=m9ueAhY5vUS3aS4H_jzoGRHLt_cCYuOkBNl2k3VqXJo&e=1773627650"
    },
    {
        "id": "7187",
        "name": "Lille at Stade Rennais (English)",
        "url": "https://mainstreams.pro/hls/dza5z8f69.m3u8?st=jBtrLv8EPv-lyNqELCBzBkEWRH-8cTPwu1qexqyIBZA&e=1773627650"
    },
    {
        "id": "7222",
        "name": "Dallas Mavericks at Cleveland Cavaliers (English)",
        "url": "https://mainstreams.pro/hls/wfazgsqtrezu66.m3u8?st=hC6j5xe378ic9cKVPEefr4AOHhCB2pGRGxF8XE6a8jo&e=1773627650"
    },
    {
        "id": "7223",
        "name": "Detroit Pistons at Toronto Raptors (English)",
        "url": "https://mainstreams.pro/hls/hfsdqtaxvb67.m3u8?st=JCZKQckjHVAYX-CHA68kt_im61PsaWBbGX4f7cEQREE&e=1773627651"
    },
    {
        "id": "7224",
        "name": "Indiana Pacers at Milwaukee Bucks (English)",
        "url": "https://mainstreams.pro/hls/zayrtezafgvdv68.m3u8?st=Pm7Tq0L-SOTc6nrzmrxWDXFGw37BW1QqW5wRd3l7xjI&e=1773627651"
    }
]